datapeek/LICENSE
datapeek/src/logger/main.py
datapeek/src/peeker/__init__.py
datapeek/src/peeker/colors.json
datapeek/src/peeker/colours_db.py
datapeek/src/peeker/dummy.py
datapeek/src/peeker/main.py
datapeek/src/peeker/peeker.py
datapeek/src/peeker/themes.py
datapeek-0.1.0.dist-info/WHEEL
datapeek-0.1.0.dist-info/METADATA
datapeek-0.1.0.dist-info/RECORD
